plaft/__main__.py
plaft-1.0.0.dist-info/LICENSE
plaft-1.0.0.dist-info/METADATA
plaft-1.0.0.dist-info/WHEEL
plaft-1.0.0.dist-info/entry_points.txt
plaft-1.0.0.dist-info/top_level.txt
plaft-1.0.0.dist-info/RECORD
