Metadata-Version: 2.1
Name: plaft
Version: 1.0.0
Summary: Simple tool for automating the correction of programming language exercises
Home-page: https://github.com/ifnmgjanauba/plaft
Author: IFNMG Campus Avançado de Janaúba
Author-email: cezarfelipe@gmail.com
License: GPLv3
Platform: UNKNOWN
Classifier: License :: OSI Approved :: GNU General Public License v3 (GPLv3)
Classifier: Intended Audience :: Education
Classifier: Programming Language :: Python :: 3
Classifier: Topic :: Education
Classifier: Topic :: Utilities
Requires-Python: >= 3.6
Requires-Dist: click
Requires-Dist: pyyaml
Requires-Dist: pexpect
